spcc/__init__.py
spcc/forms/.DS_Store
spcc/forms/__init__.py
spcc/forms/__init__.pyc
spcc/forms/common.py
spcc/forms/common.pyc
spcc/forms/field.py
spcc/forms/field.pyc
spcc/forms/__pycache__/__init__.cpython-36.pyc
spcc/forms/__pycache__/common.cpython-36.pyc
spcc/forms/__pycache__/field.cpython-36.pyc
spcc/libs/.DS_Store
spcc/libs/__init__.py
spcc/libs/security.py
spcc/libs/__pycache__/__init__.cpython-36.pyc
spcc/libs/__pycache__/security.cpython-36.pyc
spcc/models/.DS_Store
spcc/models/__init__.py
spcc/models/__init__.pyc
spcc/models/common.py
spcc/models/common.pyc
spcc/models/old_model_meta.py
spcc/models/old_model_meta.pyc
spcc/models/__pycache__/__init__.cpython-36.pyc
spcc/models/__pycache__/common.cpython-36.pyc
spcc/models/__pycache__/old_model_meta.cpython-36.pyc
spcc/static/.gitkeep
spcc/templates/.gitkeep
spcc/templates/spcc/widgets/foreign_key_select.html
spcc/templates/spcc/widgets/many_to_many_select.html
spcc/templatetags/__init__.py
spcc/templatetags/deal_time.py
spcc/templatetags/field_data_tag.py
spcc/templatetags/select_location.py
spcc/templatetags/tags.py
spcc/urls/.DS_Store
spcc/urls/__init__.py
spcc/urls/__pycache__/__init__.cpython-36.pyc
spcc/views/.DS_Store
spcc/views/__init__.py
spcc/views/__init__.pyc
spcc/views/common.py
spcc/views/common.pyc
spcc/views/__pycache__/__init__.cpython-36.pyc
spcc/views/__pycache__/common.cpython-36.pyc
django_spcc-0.2.0.dist-info/LICENSE.txt
django_spcc-0.2.0.dist-info/METADATA
django_spcc-0.2.0.dist-info/WHEEL
django_spcc-0.2.0.dist-info/dependency_links.txt
django_spcc-0.2.0.dist-info/top_level.txt
django_spcc-0.2.0.dist-info/RECORD
